simple_ado/__init__.py
simple_ado/audit.py
simple_ado/auth/__init__.py
simple_ado/auth/ado_auth.py
simple_ado/auth/ado_azid_auth.py
simple_ado/auth/ado_basic_auth.py
simple_ado/auth/ado_token_auth.py
simple_ado/base_client.py
simple_ado/builds.py
simple_ado/comments.py
simple_ado/endpoints.py
simple_ado/exceptions.py
simple_ado/git.py
simple_ado/governance.py
simple_ado/graph.py
simple_ado/http_client.py
simple_ado/identities.py
simple_ado/models/__init__.py
simple_ado/models/audit.py
simple_ado/models/operations.py
simple_ado/models/property.py
simple_ado/models/pull_requests.py
simple_ado/models/work_item_built_in_fields.py
simple_ado/models/work_item_relation_type.py
simple_ado/pipelines.py
simple_ado/pools.py
simple_ado/pull_requests.py
simple_ado/py.typed
simple_ado/security.py
simple_ado/types.py
simple_ado/user.py
simple_ado/utilities.py
simple_ado/wiki.py
simple_ado/work_item.py
simple_ado/workitems.py
simple_ado-5.1.1.dist-info/LICENSE
simple_ado-5.1.1.dist-info/METADATA
simple_ado-5.1.1.dist-info/WHEEL
simple_ado-5.1.1.dist-info/RECORD
