Metadata-Version: 2.1
Name: simple_ado
Version: 5.1.1
Summary: A simple wrapper around the Azure DevOps REST API
Home-page: https://github.com/Microsoft/simple_ado
License: MIT
Keywords: azure,devops,ado
Author: Dale Myers
Author-email: dalemy@microsoft.com
Requires-Python: >=3.10,<4.0
Classifier: Development Status :: 5 - Production/Stable
Classifier: Environment :: Console
Classifier: Environment :: MacOS X
Classifier: Intended Audience :: Developers
Classifier: License :: OSI Approved :: MIT License
Classifier: Programming Language :: Python :: 3
Classifier: Programming Language :: Python :: 3.10
Classifier: Programming Language :: Python :: 3.11
Classifier: Programming Language :: Python :: 3.12
Classifier: Programming Language :: Python :: 3.13
Classifier: Topic :: Software Development
Classifier: Topic :: Utilities
Requires-Dist: azure-identity (>=1.25.1,<2.0.0)
Requires-Dist: deserialize (>=2.2.0,<3.0.0)
Requires-Dist: requests (>=2.31.0,<3.0.0)
Requires-Dist: tenacity (>=8.2.2,<9.0.0)
Project-URL: Repository, https://github.com/Microsoft/simple_ado
